MyPMFs_py/__init__.py
MyPMFs_py/module.py
MyPMFs_py/bin/batch_download.sh
MyPMFs_py/bin/scoring
MyPMFs_py/bin/training
MyPMFs_py-0.1.8.dist-info/LICENSE.txt
MyPMFs_py-0.1.8.dist-info/METADATA
MyPMFs_py-0.1.8.dist-info/WHEEL
MyPMFs_py-0.1.8.dist-info/top_level.txt
MyPMFs_py-0.1.8.dist-info/RECORD
