Metadata-Version: 2.1
Name: MyPMFs_py
Version: 0.1.8
Summary: Python package for mypmfs training(includes batch download from PDB)
Author: Alexander Holden
Author-email: alexholden645@gmail.com
License-File: LICENSE.txt
